pagerduty/__init__.py
pagerduty/command.py
pagerduty/version.py
python3_pagerduty-0.3.0.dist-info/METADATA
python3_pagerduty-0.3.0.dist-info/WHEEL
python3_pagerduty-0.3.0.dist-info/entry_points.txt
python3_pagerduty-0.3.0.dist-info/top_level.txt
python3_pagerduty-0.3.0.dist-info/RECORD
