Metadata-Version: 2.1
Name: python3-pagerduty
Version: 0.3.0
Summary: Library for the PagerDuty service API
Home-page: http://github.com/prosperworks/python-pagerduty
Author: Samuel Stauffer
Author-email: samuel@playhaven.com
License: BSD
Platform: UNKNOWN
Classifier: Intended Audience :: Developers
Classifier: Operating System :: OS Independent
Classifier: Programming Language :: Python
Classifier: License :: OSI Approved :: BSD License
Classifier: Topic :: Software Development
Classifier: Topic :: Software Development :: Libraries
Classifier: Topic :: Software Development :: Libraries :: Python Modules
